PulseShape/PulseShape.py
PulseShape/__init__.py
PulseShape/modulations.py
PulseShape/utils.py
PulseShape-0.1.1.dist-info/LICENSE
PulseShape-0.1.1.dist-info/METADATA
PulseShape-0.1.1.dist-info/WHEEL
PulseShape-0.1.1.dist-info/top_level.txt
PulseShape-0.1.1.dist-info/RECORD
