Metadata-Version: 2.1
Name: PulseShape
Version: 0.1.1
Summary: A pulse shaping program for EPR!
Home-page: https://gitlab.com/mtessmer/PulseShape
Author: Maxx Tessmer
Author-email: mhtessmer@gmail.com
License: GNU GPLv3
Project-URL: Source, https://gitlab.com/mtessmer/PulseShape
Keywords: pulse shape,EPR,DEER,PELDOR,AWG
Platform: UNKNOWN
Classifier: License :: OSI Approved :: GNU General Public License v3 (GPLv3)
Classifier: Programming Language :: Python :: 3.6
Classifier: Programming Language :: Python :: 3.7
Classifier: Programming Language :: Python :: 3.8
Classifier: Programming Language :: Python :: 3.9
Requires-Python: >=3.6
Requires-Dist: numpy (>=1.19)
Requires-Dist: scipy (>=1.5)
